color_scheme_utils/__init__.py
color_scheme_utils/config.py
color_scheme_utils/kitty_conf_extract_theme.py
color_scheme_utils/types.py
color_scheme_utils/utils.py
color_scheme_utils-0.1.3.dist-info/entry_points.txt
color_scheme_utils-0.1.3.dist-info/LICENSE
color_scheme_utils-0.1.3.dist-info/WHEEL
color_scheme_utils-0.1.3.dist-info/METADATA
color_scheme_utils-0.1.3.dist-info/RECORD
